MANIFEST.in
README.md
setup.cfg
setup.py
bpmn_dmn/__init__.py
bpmn_dmn.egg-info/PKG-INFO
bpmn_dmn.egg-info/SOURCES.txt
bpmn_dmn.egg-info/dependency_links.txt
bpmn_dmn.egg-info/requires.txt
bpmn_dmn.egg-info/top_level.txt
bpmn_dmn.egg-info/zip-safe
bpmn_dmn/bpmn/__init__.py
bpmn_dmn/bpmn/camunda.py
bpmn_dmn/bpmn_dmn/__init__.py
bpmn_dmn/dmn/__init__.py
bpmn_dmn/dmn/engine/__init__.py
bpmn_dmn/dmn/engine/dmn_engine.py
bpmn_dmn/dmn/engine/dmn_parser.py
bpmn_dmn/dmn/engine/model.py