Metadata-Version: 1.1
Name: bpmn-dmn
Version: 0.1.7
Summary: A library to execute BPMN Workflows and DMN Decision Tables
Home-page: https://github.com/labsolutionlu/bpmn_dmn
Author: Denny Weinberg
Author-email: denny.weinberg@labsolution.lu
License: UNKNOWN
Download-URL: https://github.com/labsolutionlu/bpmn_dmn/archive/0.1.5.zip
Keywords: bpmn,dmn,camunda
Platform: UNKNOWN
